{"compilation_units": {"/Users/alpharush/tob/slither/tests/e2e/detectors/test_data/incorrect-unary/0.4.25/invalid_unary_expression.sol": {"compiler": {"compiler": "solc", "version": "0.4.25", "optimized": false}, "source_units": {"tests/e2e/detectors/test_data/incorrect-unary/0.4.25/invalid_unary_expression.sol": {"ast": {"absolutePath": "tests/e2e/detectors/test_data/incorrect-unary/0.4.25/invalid_unary_expression.sol", "exportedSymbols": {"C": [97]}, "id": 98, "nodeType": "SourceUnit", "nodes": [{"baseContracts": [], "contractDependencies": [], "contractKind": "contract", "documentation": null, "fullyImplemented": true, "id": 97, "linearizedBaseContracts": [97], "name": "C", "nodeType": "ContractDefinition", "nodes": [{"constant": false, "id": 52, "name": "a", "nodeType": "VariableDeclaration", "scope": 97, "src": "15:8:1", "stateVariable": true, "storageLocation": "default", "typeDescriptions": {"typeIdentifier": "t_uint256", "typeString": "uint256"}, "typeName": {"id": 50, "name": "uint", "nodeType": "ElementaryTypeName", "src": "15:4:1", "typeDescriptions": {"typeIdentifier": "t_uint256", "typeString": "uint256"}}, "value": {"argumentTypes": null, "hexValue": "30", "id": 51, "isConstant": false, "isLValue": false, "isPure": true, "kind": "number", "lValueRequested": false, "nodeType": "Literal", "src": "22:1:1", "subdenomination": null, "typeDescriptions": {"typeIdentifier": "t_rational_0_by_1", "typeString": "int_const 0"}, "value": "0"}, "visibility": "internal"}, {"constant": false, "id": 58, "name": "b", "nodeType": "VariableDeclaration", "scope": 97, "src": "27:11:1", "stateVariable": true, "storageLocation": "default", "typeDescriptions": {"typeIdentifier": "t_uint256", "typeString": "uint256"}, "typeName": {"id": 53, "name": "uint", "nodeType": "ElementaryTypeName", "src": "27:4:1", "typeDescriptions": {"typeIdentifier": "t_uint256", "typeString": "uint256"}}, "value": {"argumentTypes": null, "commonType": {"typeIdentifier": "t_rational_0_by_1", "typeString": "int_const 0"}, "id": 57, "isConstant": false, "isLValue": false, "isPure": true, "lValueRequested": false, "leftExpression": {"argumentTypes": null, "id": 55, "isConstant": false, "isLValue": false, "isPure": true, "lValueRequested": false, "nodeType": "UnaryOperation", "operator": "-", "prefix": true, "src": "34:2:1", "subExpression": {"argumentTypes": null, "hexValue": "31", "id": 54, "isConstant": false, "isLValue": false, "isPure": true, "kind": "number", "lValueRequested": false, "nodeType": "Literal", "src": "35:1:1", "subdenomination": null, "typeDescriptions": {"typeIdentifier": "t_rational_1_by_1", "typeString": "int_const 1"}, "value": "1"}, "typeDescriptions": {"typeIdentifier": "t_rational_-1_by_1", "typeString": "int_const -1"}}, "nodeType": "BinaryOperation", "operator": "+", "rightExpression": {"argumentTypes": null, "hexValue": "31", "id": 56, "isConstant": false, "isLValue": false, "isPure": true, "kind": "number", "lValueRequested": false, "nodeType": "Literal", "src": "37:1:1", "subdenomination": null, "typeDescriptions": {"typeIdentifier": "t_rational_1_by_1", "typeString": "int_const 1"}, "value": "1"}, "src": "34:4:1", "typeDescriptions": {"typeIdentifier": "t_rational_0_by_1", "typeString": "int_const 0"}}, "visibility": "internal"}, {"constant": false, "id": 65, "name": "c", "nodeType": "VariableDeclaration", "scope": 97, "src": "42:13:1", "stateVariable": true, "storageLocation": "default", "typeDescriptions": {"typeIdentifier": "t_uint256", "typeString": "uint256"}, "typeName": {"id": 59, "name": "uint", "nodeType": "ElementaryTypeName", "src": "42:4:1", "typeDescriptions": {"typeIdentifier": "t_uint256", "typeString": "uint256"}}, "value": {"argumentTypes": null, "components": [{"argumentTypes": null, "id": 63, "isConstant": false, "isLValue": false, "isPure": false, "lValueRequested": false, "leftHandSide": {"argumentTypes": null, "id": 60, "name": "b", "nodeType": "Identifier", "overloadedDeclarations": [], "referencedDeclaration": 58, "src": "50:1:1", "typeDescriptions": {"typeIdentifier": "t_uint256", "typeString": "uint256"}}, "nodeType": "Assignment", "operator": "=", "rightHandSide": {"argumentTypes": null, "id": 62, "isConstant": false, "isLValue": false, "isPure": true, "lValueRequested": false, "nodeType": "UnaryOperation", "operator": "+", "prefix": true, "src": "52:2:1", "subExpression": {"argumentTypes": null, "hexValue": "31", "id": 61, "isConstant": false, "isLValue": false, "isPure": true, "kind": "number", "lValueRequested": false, "nodeType": "Literal", "src": "53:1:1", "subdenomination": null, "typeDescriptions": {"typeIdentifier": "t_rational_1_by_1", "typeString": "int_const 1"}, "value": "1"}, "typeDescriptions": {"typeIdentifier": "t_rational_1_by_1", "typeString": "int_const 1"}}, "src": "50:4:1", "typeDescriptions": {"typeIdentifier": "t_uint256", "typeString": "uint256"}}], "id": 64, "isConstant": false, "isInlineArray": false, "isLValue": false, "isPure": false, "lValueRequested": false, "nodeType": "TupleExpression", "src": "49:6:1", "typeDescriptions": {"typeIdentifier": "t_uint256", "typeString": "uint256"}}, "visibility": "internal"}, {"body": {"id": 95, "nodeType": "Block", "src": "82:120:1", "statements": [{"assignments": [69], "declarations": [{"constant": false, "id": 69, "name": "x", "nodeType": "VariableDeclaration", "scope": 96, "src": "88:6:1", "stateVariable": false, "storageLocation": "default", "typeDescriptions": {"typeIdentifier": "t_uint256", "typeString": "uint256"}, "typeName": {"id": 68, "name": "uint", "nodeType": "ElementaryTypeName", "src": "88:4:1", "typeDescriptions": {"typeIdentifier": "t_uint256", "typeString": "uint256"}}, "value": null, "visibility": "internal"}], "id": 71, "initialValue": {"argumentTypes": null, "hexValue": "31", "id": 70, "isConstant": false, "isLValue": false, "isPure": true, "kind": "number", "lValueRequested": false, "nodeType": "Literal", "src": "97:1:1", "subdenomination": null, "typeDescriptions": {"typeIdentifier": "t_rational_1_by_1", "typeString": "int_const 1"}, "value": "1"}, "nodeType": "VariableDeclarationStatement", "src": "88:10:1"}, {"expression": {"argumentTypes": null, "id": 75, "isConstant": false, "isLValue": false, "isPure": false, "lValueRequested": false, "leftHandSide": {"argumentTypes": null, "id": 72, "name": "x", "nodeType": "Identifier", "overloadedDeclarations": [], "referencedDeclaration": 69, "src": "104:1:1", "typeDescriptions": {"typeIdentifier": "t_uint256", "typeString": "uint256"}}, "nodeType": "Assignment", "operator": "=", "rightHandSide": {"argumentTypes": null, "id": 74, "isConstant": false, "isLValue": false, "isPure": true, "lValueRequested": false, "nodeType": "UnaryOperation", "operator": "+", "prefix": true, "src": "106:24:1", "subExpression": {"argumentTypes": null, "hexValue": "313434343434", "id": 73, "isConstant": false, "isLValue": false, "isPure": true, "kind": "number", "lValueRequested": false, "nodeType": "Literal", "src": "124:6:1", "subdenomination": null, "typeDescriptions": {"typeIdentifier": "t_rational_144444_by_1", "typeString": "int_const 144444"}, "value": "144444"}, "typeDescriptions": {"typeIdentifier": "t_rational_144444_by_1", "typeString": "int_const 144444"}}, "src": "104:26:1", "typeDescriptions": {"typeIdentifier": "t_uint256", "typeString": "uint256"}}, "id": 76, "nodeType": "ExpressionStatement", "src": "104:26:1"}, {"expression": {"argumentTypes": null, "id": 83, "isConstant": false, "isLValue": false, "isPure": false, "lValueRequested": false, "leftHandSide": {"argumentTypes": null, "id": 77, "name": "x", "nodeType": "Identifier", "overloadedDeclarations": [], "referencedDeclaration": 69, "src": "136:1:1", "typeDescriptions": {"typeIdentifier": "t_uint256", "typeString": "uint256"}}, "nodeType": "Assignment", "operator": "=", "rightHandSide": {"argumentTypes": null, "components": [{"argumentTypes": null, "id": 81, "isConstant": false, "isLValue": false, "isPure": false, "lValueRequested": false, "leftHandSide": {"argumentTypes": null, "id": 78, "name": "x", "nodeType": "Identifier", "overloadedDeclarations": [], "referencedDeclaration": 69, "src": "141:1:1", "typeDescriptions": {"typeIdentifier": "t_uint256", "typeString": "uint256"}}, "nodeType": "Assignment", "operator": "=", "rightHandSide": {"argumentTypes": null, "id": 80, "isConstant": false, "isLValue": false, "isPure": true, "lValueRequested": false, "nodeType": "UnaryOperation", "operator": "+", "prefix": true, "src": "143:2:1", "subExpression": {"argumentTypes": null, "hexValue": "31", "id": 79, "isConstant": false, "isLValue": false, "isPure": true, "kind": "number", "lValueRequested": false, "nodeType": "Literal", "src": "144:1:1", "subdenomination": null, "typeDescriptions": {"typeIdentifier": "t_rational_1_by_1", "typeString": "int_const 1"}, "value": "1"}, "typeDescriptions": {"typeIdentifier": "t_rational_1_by_1", "typeString": "int_const 1"}}, "src": "141:4:1", "typeDescriptions": {"typeIdentifier": "t_uint256", "typeString": "uint256"}}], "id": 82, "isConstant": false, "isInlineArray": false, "isLValue": false, "isPure": false, "lValueRequested": false, "nodeType": "TupleExpression", "src": "140:6:1", "typeDescriptions": {"typeIdentifier": "t_uint256", "typeString": "uint256"}}, "src": "136:10:1", "typeDescriptions": {"typeIdentifier": "t_uint256", "typeString": "uint256"}}, "id": 84, "nodeType": "ExpressionStatement", "src": "136:10:1"}, {"expression": {"argumentTypes": null, "id": 86, "isConstant": false, "isLValue": false, "isPure": false, "lValueRequested": false, "nodeType": "UnaryOperation", "operator": "++", "prefix": false, "src": "152:3:1", "subExpression": {"argumentTypes": null, "id": 85, "name": "x", "nodeType": "Identifier", "overloadedDeclarations": [], "referencedDeclaration": 69, "src": "152:1:1", "typeDescriptions": {"typeIdentifier": "t_uint256", "typeString": "uint256"}}, "typeDescriptions": {"typeIdentifier": "t_uint256", "typeString": "uint256"}}, "id": 87, "nodeType": "ExpressionStatement", "src": "152:3:1"}, {"expression": {"argumentTypes": null, "id": 93, "isConstant": false, "isLValue": false, "isPure": false, "lValueRequested": false, "leftHandSide": {"argumentTypes": null, "id": 88, "name": "x", "nodeType": "Identifier", "overloadedDeclarations": [], "referencedDeclaration": 69, "src": "161:1:1", "typeDescriptions": {"typeIdentifier": "t_uint256", "typeString": "uint256"}}, "nodeType": "Assignment", "operator": "=", "rightHandSide": {"argumentTypes": null, "commonType": {"typeIdentifier": "t_rational_0_by_1", "typeString": "int_const 0"}, "id": 92, "isConstant": false, "isLValue": false, "isPure": true, "lValueRequested": false, "leftExpression": {"argumentTypes": null, "id": 90, "isConstant": false, "isLValue": false, "isPure": true, "lValueRequested": false, "nodeType": "UnaryOperation", "operator": "-", "prefix": true, "src": "165:2:1", "subExpression": {"argumentTypes": null, "hexValue": "31", "id": 89, "isConstant": false, "isLValue": false, "isPure": true, "kind": "number", "lValueRequested": false, "nodeType": "Literal", "src": "166:1:1", "subdenomination": null, "typeDescriptions": {"typeIdentifier": "t_rational_1_by_1", "typeString": "int_const 1"}, "value": "1"}, "typeDescriptions": {"typeIdentifier": "t_rational_-1_by_1", "typeString": "int_const -1"}}, "nodeType": "BinaryOperation", "operator": "+", "rightExpression": {"argumentTypes": null, "hexValue": "31", "id": 91, "isConstant": false, "isLValue": false, "isPure": true, "kind": "number", "lValueRequested": false, "nodeType": "Literal", "src": "170:1:1", "subdenomination": null, "typeDescriptions": {"typeIdentifier": "t_rational_1_by_1", "typeString": "int_const 1"}, "value": "1"}, "src": "165:6:1", "typeDescriptions": {"typeIdentifier": "t_rational_0_by_1", "typeString": "int_const 0"}}, "src": "161:10:1", "typeDescriptions": {"typeIdentifier": "t_uint256", "typeString": "uint256"}}, "id": 94, "nodeType": "ExpressionStatement", "src": "161:10:1"}]}, "documentation": null, "id": 96, "implemented": true, "isConstructor": false, "isDeclaredConst": false, "modifiers": [], "name": "f", "nodeType": "FunctionDefinition", "parameters": {"id": 66, "nodeType": "ParameterList", "parameters": [], "src": "70:2:1"}, "payable": false, "returnParameters": {"id": 67, "nodeType": "ParameterList", "parameters": [], "src": "82:0:1"}, "scope": 97, "src": "60:142:1", "stateMutability": "nonpayable", "superFunction": null, "visibility": "external"}], "scope": 98, "src": "0:204:1"}], "src": "0:205:1"}, "contracts": {"C": {"abi": [{"constant": false, "inputs": [], "name": "f", "outputs": [], "payable": false, "stateMutability": "nonpayable", "type": "function"}], "bin": "6080604052600080556000600155600180819055600255348015602157600080fd5b5060a6806100306000396000f300608060405260043610603f576000357c0100000000000000000000000000000000000000000000000000000000900463ffffffff16806326121ff0146044575b600080fd5b348015604f57600080fd5b5060566058565b005b6000600190506202343c905060019050809050808060010191505060009050505600a165627a7a72305820909e21a03ed7d3c9953cd0debd75bca6ff240d91423ca3e6e55255779d1552430029", "bin-runtime": "608060405260043610603f576000357c0100000000000000000000000000000000000000000000000000000000900463ffffffff16806326121ff0146044575b600080fd5b348015604f57600080fd5b5060566058565b005b6000600190506202343c905060019050809050808060010191505060009050505600a165627a7a72305820909e21a03ed7d3c9953cd0debd75bca6ff240d91423ca3e6e55255779d1552430029", "srcmap": "0:204:1:-;;;22:1;15:8;;34:4;27:11;;52:2;50:1;:4;;;42:13;;0:204;8:9:-1;5:2;;;30:1;27;20:12;5:2;0:204:1;;;;;;;", "srcmap-runtime": "0:204:1:-;;;;;;;;;;;;;;;;;;;;;;;;60:142;;8:9:-1;5:2;;;30:1;27;20:12;5:2;60:142:1;;;;;;;88:6;97:1;88:10;;106:24;104:26;;143:2;141:4;;;136:10;;152:3;;;;;;;165:6;161:10;;60:142;:::o", "filenames": {"absolute": "/Users/alpharush/tob/slither/tests/e2e/detectors/test_data/incorrect-unary/0.4.25/invalid_unary_expression.sol", "used": "tests/e2e/detectors/test_data/incorrect-unary/0.4.25/invalid_unary_expression.sol", "short": "tests/e2e/detectors/test_data/incorrect-unary/0.4.25/invalid_unary_expression.sol", "relative": "tests/e2e/detectors/test_data/incorrect-unary/0.4.25/invalid_unary_expression.sol"}, "libraries": {}, "is_dependency": false, "userdoc": {"methods": {}, "notice": null}, "devdoc": {"methods": {}, "author": null, "details": null, "title": null}}}}}, "filenames": [{"absolute": "/Users/alpharush/tob/slither/tests/e2e/detectors/test_data/incorrect-unary/0.4.25/invalid_unary_expression.sol", "used": "tests/e2e/detectors/test_data/incorrect-unary/0.4.25/invalid_unary_expression.sol", "short": "tests/e2e/detectors/test_data/incorrect-unary/0.4.25/invalid_unary_expression.sol", "relative": "tests/e2e/detectors/test_data/incorrect-unary/0.4.25/invalid_unary_expression.sol"}, {"absolute": "/Users/alpharush/tob/slither/tests/e2e/detectors/test_data/incorrect-unary/0.4.25/invalid_unary_expression.sol", "used": "/Users/alpharush/tob/slither/tests/e2e/detectors/test_data/incorrect-unary/0.4.25/invalid_unary_expression.sol", "short": "tests/e2e/detectors/test_data/incorrect-unary/0.4.25/invalid_unary_expression.sol", "relative": "tests/e2e/detectors/test_data/incorrect-unary/0.4.25/invalid_unary_expression.sol"}]}}, "package": null, "working_dir": "/Users/alpharush/tob/slither", "type": 1, "unit_tests": [], "crytic_version": "0.0.2", "source_content": {"/Users/alpharush/tob/slither/tests/e2e/detectors/test_data/incorrect-unary/0.4.25/invalid_unary_expression.sol": "contract C {\n  uint a=0;\n  uint b=-1+1;\n  uint c=(b=+1);\n\n  function f() external {\n    uint x = 1;\n    x=+                 144444;\n    x = (x=+1);\n    x++;\n    x = -1 + 1;\n    //++x;\n    //x = x++;\n  }\n}\n"}}