{"compilation_units": {"/Users/alpharush/tob/slither/tests/e2e/detectors/test_data/rtlo/0.5.16/right_to_left_override.sol": {"compiler": {"compiler": "solc", "version": "0.5.16", "optimized": false}, "source_units": {"tests/e2e/detectors/test_data/rtlo/0.5.16/right_to_left_override.sol": {"ast": {"absolutePath": "tests/e2e/detectors/test_data/rtlo/0.5.16/right_to_left_override.sol", "exportedSymbols": {"A": [55]}, "id": 56, "nodeType": "SourceUnit", "nodes": [{"baseContracts": [], "contractDependencies": [], "contractKind": "contract", "documentation": null, "fullyImplemented": true, "id": 55, "linearizedBaseContracts": [55], "name": "A", "nodeType": "ContractDefinition", "nodes": [{"body": {"id": 37, "nodeType": "Block", "src": "77:64:1", "statements": [{"expression": {"argumentTypes": null, "arguments": [{"argumentTypes": null, "hexValue": "32", "id": 32, "isConstant": false, "isLValue": false, "isPure": true, "kind": "number", "lValueRequested": false, "nodeType": "Literal", "src": "104:1:1", "subdenomination": null, "typeDescriptions": {"typeIdentifier": "t_rational_2_by_1", "typeString": "int_const 2"}, "value": "2"}, {"argumentTypes": null, "hexValue": "31", "id": 33, "isConstant": false, "isLValue": false, "isPure": true, "kind": "number", "lValueRequested": false, "nodeType": "Literal", "src": "108:1:1", "subdenomination": null, "typeDescriptions": {"typeIdentifier": "t_rational_1_by_1", "typeString": "int_const 1"}, "value": "1"}, {"argumentTypes": null, "hexValue": "33", "id": 34, "isConstant": false, "isLValue": false, "isPure": true, "kind": "number", "lValueRequested": false, "nodeType": "Literal", "src": "132:1:1", "subdenomination": null, "typeDescriptions": {"typeIdentifier": "t_rational_3_by_1", "typeString": "int_const 3"}, "value": "3"}], "expression": {"argumentTypes": [{"typeIdentifier": "t_rational_2_by_1", "typeString": "int_const 2"}, {"typeIdentifier": "t_rational_1_by_1", "typeString": "int_const 1"}, {"typeIdentifier": "t_rational_3_by_1", "typeString": "int_const 3"}], "id": 31, "name": "test1", "nodeType": "Identifier", "overloadedDeclarations": [], "referencedDeclaration": 54, "src": "87:5:1", "typeDescriptions": {"typeIdentifier": "t_function_internal_pure$_t_uint256_$_t_uint256_$_t_uint256_$returns$__$", "typeString": "function (uint256,uint256,uint256) pure"}}, "id": 35, "isConstant": false, "isLValue": false, "isPure": false, "kind": "functionCall", "lValueRequested": false, "names": [], "nodeType": "FunctionCall", "src": "87:47:1", "typeDescriptions": {"typeIdentifier": "t_tuple$__$", "typeString": "tuple()"}}, "id": 36, "nodeType": "ExpressionStatement", "src": "87:47:1"}]}, "documentation": null, "id": 38, "implemented": true, "kind": "function", "modifiers": [], "name": "test", "nodeType": "FunctionDefinition", "parameters": {"id": 29, "nodeType": "ParameterList", "parameters": [], "src": "58:2:1"}, "returnParameters": {"id": 30, "nodeType": "ParameterList", "parameters": [], "src": "77:0:1"}, "scope": 55, "src": "45:96:1", "stateMutability": "pure", "superFunction": null, "visibility": "public"}, {"body": {"id": 53, "nodeType": "Block", "src": "208:20:1", "statements": [{"expression": {"argumentTypes": null, "id": 51, "isConstant": false, "isLValue": false, "isPure": false, "lValueRequested": false, "leftHandSide": {"argumentTypes": null, "id": 47, "name": "a", "nodeType": "Identifier", "overloadedDeclarations": [], "referencedDeclaration": 40, "src": "212:1:1", "typeDescriptions": {"typeIdentifier": "t_uint256", "typeString": "uint256"}}, "nodeType": "Assignment", "operator": "=", "rightHandSide": {"argumentTypes": null, "commonType": {"typeIdentifier": "t_uint256", "typeString": "uint256"}, "id": 50, "isConstant": false, "isLValue": false, "isPure": false, "lValueRequested": false, "leftExpression": {"argumentTypes": null, "id": 48, "name": "b", "nodeType": "Identifier", "overloadedDeclarations": [], "referencedDeclaration": 42, "src": "216:1:1", "typeDescriptions": {"typeIdentifier": "t_uint256", "typeString": "uint256"}}, "nodeType": "BinaryOperation", "operator": "+", "rightExpression": {"argumentTypes": null, "id": 49, "name": "c", "nodeType": "Identifier", "overloadedDeclarations": [], "referencedDeclaration": 44, "src": "220:1:1", "typeDescriptions": {"typeIdentifier": "t_uint256", "typeString": "uint256"}}, "src": "216:5:1", "typeDescriptions": {"typeIdentifier": "t_uint256", "typeString": "uint256"}}, "src": "212:9:1", "typeDescriptions": {"typeIdentifier": "t_uint256", "typeString": "uint256"}}, "id": 52, "nodeType": "ExpressionStatement", "src": "212:9:1"}]}, "documentation": null, "id": 54, "implemented": true, "kind": "function", "modifiers": [], "name": "test1", "nodeType": "FunctionDefinition", "parameters": {"id": 45, "nodeType": "ParameterList", "parameters": [{"constant": false, "id": 40, "name": "a", "nodeType": "VariableDeclaration", "scope": 54, "src": "166:6:1", "stateVariable": false, "storageLocation": "default", "typeDescriptions": {"typeIdentifier": "t_uint256", "typeString": "uint256"}, "typeName": {"id": 39, "name": "uint", "nodeType": "ElementaryTypeName", "src": "166:4:1", "typeDescriptions": {"typeIdentifier": "t_uint256", "typeString": "uint256"}}, "value": null, "visibility": "internal"}, {"constant": false, "id": 42, "name": "b", "nodeType": "VariableDeclaration", "scope": 54, "src": "174:6:1", "stateVariable": false, "storageLocation": "default", "typeDescriptions": {"typeIdentifier": "t_uint256", "typeString": "uint256"}, "typeName": {"id": 41, "name": "uint", "nodeType": "ElementaryTypeName", "src": "174:4:1", "typeDescriptions": {"typeIdentifier": "t_uint256", "typeString": "uint256"}}, "value": null, "visibility": "internal"}, {"constant": false, "id": 44, "name": "c", "nodeType": "VariableDeclaration", "scope": 54, "src": "182:6:1", "stateVariable": false, "storageLocation": "default", "typeDescriptions": {"typeIdentifier": "t_uint256", "typeString": "uint256"}, "typeName": {"id": 43, "name": "uint", "nodeType": "ElementaryTypeName", "src": "182:4:1", "typeDescriptions": {"typeIdentifier": "t_uint256", "typeString": "uint256"}}, "value": null, "visibility": "internal"}], "src": "165:24:1"}, "returnParameters": {"id": 46, "nodeType": "ParameterList", "parameters": [], "src": "208:0:1"}, "scope": 55, "src": "151:77:1", "stateMutability": "pure", "superFunction": null, "visibility": "internal"}], "scope": 56, "src": "28:202:1"}], "src": "28:203:1"}, "contracts": {"A": {"abi": [{"constant": true, "inputs": [], "name": "test", "outputs": [], "payable": false, "stateMutability": "pure", "type": "function"}], "bin": "6080604052348015600f57600080fd5b5060828061001e6000396000f3fe6080604052348015600f57600080fd5b506004361060285760003560e01c8063f8a8fd6d14602d575b600080fd5b60336035565b005b60416002600160036043565b565b808201925050505056fea265627a7a723158209d13d7dcafe494875f74949a702fcf029042499af66042bf3b4dd8e1cf0a6ff864736f6c63430005100032", "bin-runtime": "6080604052348015600f57600080fd5b506004361060285760003560e01c8063f8a8fd6d14602d575b600080fd5b60336035565b005b60416002600160036043565b565b808201925050505056fea265627a7a723158209d13d7dcafe494875f74949a702fcf029042499af66042bf3b4dd8e1cf0a6ff864736f6c63430005100032", "srcmap": "28:202:1:-;;;;8:9:-1;5:2;;;30:1;27;20:12;5:2;28:202:1;;;;;;;", "srcmap-runtime": "28:202:1:-;;;;8:9:-1;5:2;;;30:1;27;20:12;5:2;28:202:1;;;;;;;;;;;;;;;;;;;45:96;;;:::i;:::-;;;87:47;104:1;108;132;87:5;:47::i;:::-;45:96::o;151:77::-;220:1;216;:5;212:9;;151:77;;;:::o", "filenames": {"absolute": "/Users/alpharush/tob/slither/tests/e2e/detectors/test_data/rtlo/0.5.16/right_to_left_override.sol", "used": "tests/e2e/detectors/test_data/rtlo/0.5.16/right_to_left_override.sol", "short": "tests/e2e/detectors/test_data/rtlo/0.5.16/right_to_left_override.sol", "relative": "tests/e2e/detectors/test_data/rtlo/0.5.16/right_to_left_override.sol"}, "libraries": {}, "is_dependency": false, "userdoc": {"methods": {}, "notice": null}, "devdoc": {"methods": {}, "author": null, "details": null, "title": null}}}}}, "filenames": [{"absolute": "/Users/alpharush/tob/slither/tests/e2e/detectors/test_data/rtlo/0.5.16/right_to_left_override.sol", "used": "/Users/alpharush/tob/slither/tests/e2e/detectors/test_data/rtlo/0.5.16/right_to_left_override.sol", "short": "tests/e2e/detectors/test_data/rtlo/0.5.16/right_to_left_override.sol", "relative": "tests/e2e/detectors/test_data/rtlo/0.5.16/right_to_left_override.sol"}, {"absolute": "/Users/alpharush/tob/slither/tests/e2e/detectors/test_data/rtlo/0.5.16/right_to_left_override.sol", "used": "tests/e2e/detectors/test_data/rtlo/0.5.16/right_to_left_override.sol", "short": "tests/e2e/detectors/test_data/rtlo/0.5.16/right_to_left_override.sol", "relative": "tests/e2e/detectors/test_data/rtlo/0.5.16/right_to_left_override.sol"}]}}, "package": null, "working_dir": "/Users/alpharush/tob/slither", "type": 1, "unit_tests": [], "crytic_version": "0.0.2", "source_content": {"/Users/alpharush/tob/slither/tests/e2e/detectors/test_data/rtlo/0.5.16/right_to_left_override.sol": "//pragma solidity ^0.4.24;\n\ncontract A\n{\n    function test() public pure\n    {\n        test1(/*A\u202e/*B*/2 , 1/*\u202d\n\t\t        /*C */,3);\n    }\n    \n    function test1(uint a, uint b, uint c) internal pure\n    {\n\t\ta = b + c;\n    }\n}\n"}}