{"compilation_units": {"/home/monty/tob/tools/slither/tests/ast-parsing/binaryoperation-0.4.0.sol": {"compiler": {"compiler": "solc", "version": "0.4.0", "optimized": false}, "asts": {"/home/monty/tob/tools/slither/tests/ast-parsing/binaryoperation-0.4.0.sol": {"children": [{"attributes": {"fullyImplemented": true, "isLibrary": false, "linearizedBaseContracts": [43624048], "name": "C"}, "children": [{"attributes": {"constant": false, "name": "f", "public": true}, "children": [{"children": [], "id": 43598160, "name": "ParameterList", "src": "27:2:1"}, {"children": [], "id": 43607584, "name": "ParameterList", "src": "37:0:1"}, {"children": [{"children": [{"attributes": {"operator": "**", "type": "int_const 1"}, "children": [{"attributes": {"hexvalue": "31", "subdenomination": null, "token": null, "type": "int_const 1", "value": "1"}, "id": 43607744, "name": "Literal", "src": "47:1:1"}, {"attributes": {"hexvalue": "32", "subdenomination": null, "token": null, "type": "int_const 2", "value": "2"}, "id": 43611664, "name": "Literal", "src": "50:1:1"}], "id": 43611760, "name": "BinaryOperation", "src": "47:4:1"}], "id": 43611872, "name": "ExpressionStatement", "src": "47:4:1"}, {"children": [{"attributes": {"operator": "*", "type": "int_const 2"}, "children": [{"attributes": {"hexvalue": "31", "subdenomination": null, "token": null, "type": "int_const 1", "value": "1"}, "id": 43612032, "name": "Literal", "src": "61:1:1"}, {"attributes": {"hexvalue": "32", "subdenomination": null, "token": null, "type": "int_const 2", "value": "2"}, "id": 43612192, "name": "Literal", "src": "63:1:1"}], "id": 43612288, "name": "BinaryOperation", "src": "61:3:1"}], "id": 43612400, "name": "ExpressionStatement", "src": "61:3:1"}, {"children": [{"attributes": {"operator": "/", "type": "rational_const 1/2"}, "children": [{"attributes": {"hexvalue": "31", "subdenomination": null, "token": null, "type": "int_const 1", "value": "1"}, "id": 43612560, "name": "Literal", "src": "74:1:1"}, {"attributes": {"hexvalue": "32", "subdenomination": null, "token": null, "type": "int_const 2", "value": "2"}, "id": 43612720, "name": "Literal", "src": "76:1:1"}], "id": 43612816, "name": "BinaryOperation", "src": "74:3:1"}], "id": 43612928, "name": "ExpressionStatement", "src": "74:3:1"}, {"children": [{"attributes": {"operator": "&", "type": "int_const 0"}, "children": [{"attributes": {"hexvalue": "31", "subdenomination": null, "token": null, "type": "int_const 1", "value": "1"}, "id": 43613168, "name": "Literal", "src": "87:1:1"}, {"attributes": {"hexvalue": "32", "subdenomination": null, "token": null, "type": "int_const 2", "value": "2"}, "id": 43613328, "name": "Literal", "src": "89:1:1"}], "id": 43613424, "name": "BinaryOperation", "src": "87:3:1"}], "id": 43613536, "name": "ExpressionStatement", "src": "87:3:1"}, {"children": [{"attributes": {"operator": "+", "type": "int_const 3"}, "children": [{"attributes": {"hexvalue": "31", "subdenomination": null, "token": null, "type": "int_const 1", "value": "1"}, "id": 43613696, "name": "Literal", "src": "100:1:1"}, {"attributes": {"hexvalue": "32", "subdenomination": null, "token": null, "type": "int_const 2", "value": "2"}, "id": 43613856, "name": "Literal", "src": "102:1:1"}], "id": 43613952, "name": "BinaryOperation", "src": "100:3:1"}], "id": 43614064, "name": "ExpressionStatement", "src": "100:3:1"}, {"children": [{"attributes": {"operator": "-", "type": "int_const -1"}, "children": [{"attributes": {"hexvalue": "31", "subdenomination": null, "token": null, "type": "int_const 1", "value": "1"}, "id": 43614368, "name": "Literal", "src": "113:1:1"}, {"attributes": {"hexvalue": "32", "subdenomination": null, "token": null, "type": "int_const 2", "value": "2"}, "id": 43617568, "name": "Literal", "src": "115:1:1"}], "id": 43617664, "name": "BinaryOperation", "src": "113:3:1"}], "id": 43617776, "name": "ExpressionStatement", "src": "113:3:1"}, {"children": [{"attributes": {"operator": "&", "type": "int_const 0"}, "children": [{"attributes": {"hexvalue": "31", "subdenomination": null, "token": null, "type": "int_const 1", "value": "1"}, "id": 43617936, "name": "Literal", "src": "126:1:1"}, {"attributes": {"hexvalue": "32", "subdenomination": null, "token": null, "type": "int_const 2", "value": "2"}, "id": 43618096, "name": "Literal", "src": "130:1:1"}], "id": 43618192, "name": "BinaryOperation", "src": "126:5:1"}], "id": 43618304, "name": "ExpressionStatement", "src": "126:5:1"}, {"children": [{"attributes": {"operator": "^", "type": "int_const 3"}, "children": [{"attributes": {"hexvalue": "31", "subdenomination": null, "token": null, "type": "int_const 1", "value": "1"}, "id": 43618464, "name": "Literal", "src": "141:1:1"}, {"attributes": {"hexvalue": "32", "subdenomination": null, "token": null, "type": "int_const 2", "value": "2"}, "id": 43618624, "name": "Literal", "src": "145:1:1"}], "id": 43618720, "name": "BinaryOperation", "src": "141:5:1"}], "id": 43618832, "name": "ExpressionStatement", "src": "141:5:1"}, {"children": [{"attributes": {"operator": "|", "type": "int_const 3"}, "children": [{"attributes": {"hexvalue": "31", "subdenomination": null, "token": null, "type": "int_const 1", "value": "1"}, "id": 43618992, "name": "Literal", "src": "156:1:1"}, {"attributes": {"hexvalue": "32", "subdenomination": null, "token": null, "type": "int_const 2", "value": "2"}, "id": 43619152, "name": "Literal", "src": "160:1:1"}], "id": 43619248, "name": "BinaryOperation", "src": "156:5:1"}], "id": 43619360, "name": "ExpressionStatement", "src": "156:5:1"}, {"children": [{"attributes": {"operator": "<", "type": "bool"}, "children": [{"attributes": {"hexvalue": "31", "subdenomination": null, "token": null, "type": "int_const 1", "value": "1"}, "id": 43619728, "name": "Literal", "src": "171:1:1"}, {"attributes": {"hexvalue": "32", "subdenomination": null, "token": null, "type": "int_const 2", "value": "2"}, "id": 43619824, "name": "Literal", "src": "175:1:1"}], "id": 43619920, "name": "BinaryOperation", "src": "171:5:1"}], "id": 43620032, "name": "ExpressionStatement", "src": "171:5:1"}, {"children": [{"attributes": {"operator": ">", "type": "bool"}, "children": [{"attributes": {"hexvalue": "31", "subdenomination": null, "token": null, "type": "int_const 1", "value": "1"}, "id": 43620192, "name": "Literal", "src": "186:1:1"}, {"attributes": {"hexvalue": "32", "subdenomination": null, "token": null, "type": "int_const 2", "value": "2"}, "id": 43620352, "name": "Literal", "src": "190:1:1"}], "id": 43620448, "name": "BinaryOperation", "src": "186:5:1"}], "id": 43620560, "name": "ExpressionStatement", "src": "186:5:1"}, {"children": [{"attributes": {"operator": "<=", "type": "bool"}, "children": [{"attributes": {"hexvalue": "31", "subdenomination": null, "token": null, "type": "int_const 1", "value": "1"}, "id": 43620720, "name": "Literal", "src": "201:1:1"}, {"attributes": {"hexvalue": "32", "subdenomination": null, "token": null, "type": "int_const 2", "value": "2"}, "id": 43620880, "name": "Literal", "src": "206:1:1"}], "id": 43620976, "name": "BinaryOperation", "src": "201:6:1"}], "id": 43621088, "name": "ExpressionStatement", "src": "201:6:1"}, {"children": [{"attributes": {"operator": ">=", "type": "bool"}, "children": [{"attributes": {"hexvalue": "31", "subdenomination": null, "token": null, "type": "int_const 1", "value": "1"}, "id": 43621248, "name": "Literal", "src": "217:1:1"}, {"attributes": {"hexvalue": "32", "subdenomination": null, "token": null, "type": "int_const 2", "value": "2"}, "id": 43621408, "name": "Literal", "src": "222:1:1"}], "id": 43621504, "name": "BinaryOperation", "src": "217:6:1"}], "id": 43621616, "name": "ExpressionStatement", "src": "217:6:1"}, {"children": [{"attributes": {"operator": "==", "type": "bool"}, "children": [{"attributes": {"hexvalue": "31", "subdenomination": null, "token": null, "type": "int_const 1", "value": "1"}, "id": 43621776, "name": "Literal", "src": "233:1:1"}, {"attributes": {"hexvalue": "32", "subdenomination": null, "token": null, "type": "int_const 2", "value": "2"}, "id": 43621936, "name": "Literal", "src": "238:1:1"}], "id": 43622032, "name": "BinaryOperation", "src": "233:6:1"}], "id": 43622144, "name": "ExpressionStatement", "src": "233:6:1"}, {"children": [{"attributes": {"operator": "!=", "type": "bool"}, "children": [{"attributes": {"hexvalue": "31", "subdenomination": null, "token": null, "type": "int_const 1", "value": "1"}, "id": 43622304, "name": "Literal", "src": "249:1:1"}, {"attributes": {"hexvalue": "32", "subdenomination": null, "token": null, "type": "int_const 2", "value": "2"}, "id": 43622464, "name": "Literal", "src": "254:1:1"}], "id": 43622560, "name": "BinaryOperation", "src": "249:6:1"}], "id": 43622672, "name": "ExpressionStatement", "src": "249:6:1"}, {"children": [{"attributes": {"operator": "&&", "type": "bool"}, "children": [{"attributes": {"hexvalue": "74727565", "subdenomination": null, "token": "true", "type": "bool", "value": "true"}, "id": 43622832, "name": "Literal", "src": "265:4:1"}, {"attributes": {"hexvalue": "66616c7365", "subdenomination": null, "token": "false", "type": "bool", "value": "false"}, "id": 43622992, "name": "Literal", "src": "273:5:1"}], "id": 43623088, "name": "BinaryOperation", "src": "265:13:1"}], "id": 43623200, "name": "ExpressionStatement", "src": "265:13:1"}, {"children": [{"attributes": {"operator": "||", "type": "bool"}, "children": [{"attributes": {"hexvalue": "74727565", "subdenomination": null, "token": "true", "type": "bool", "value": "true"}, "id": 43623360, "name": "Literal", "src": "288:4:1"}, {"attributes": {"hexvalue": "66616c7365", "subdenomination": null, "token": "false", "type": "bool", "value": "false"}, "id": 43623520, "name": "Literal", "src": "296:5:1"}], "id": 43623616, "name": "BinaryOperation", "src": "288:13:1"}], "id": 43623728, "name": "ExpressionStatement", "src": "288:13:1"}], "id": 43619456, "name": "Block", "src": "37:271:1"}], "id": 43623824, "name": "FunctionDefinition", "src": "17:291:1"}], "id": 43624048, "name": "ContractDefinition", "src": "0:311:1"}], "name": "SourceUnit"}}, "contracts": {"tests/ast-parsing/binaryoperation-0.4.0.sol": {"C": {"abi": [{"constant": false, "inputs": [], "name": "f", "outputs": [], "payable": false, "type": "function"}], "bin": "606060405260c58060106000396000f360606040526000357c01000000000000000000000000000000000000000000000000000000009004806326121ff0146039576035565b6002565b3460025760486004805050604a565b005b6001506002506080506000506003507fffffffffffffffffffffffffffffffffffffffffffffffffffffffffffffffff506000506003506003506002600110506002600111506002600111155060026001101550600260011450600260011415506001801560b6575060005b5060018060c1575060005b505b56", "bin-runtime": "60606040526000357c01000000000000000000000000000000000000000000000000000000009004806326121ff0146039576035565b6002565b3460025760486004805050604a565b005b6001506002506080506000506003507fffffffffffffffffffffffffffffffffffffffffffffffffffffffffffffffff506000506003506003506002600110506002600111506002600111155060026001101550600260011450600260011415506001801560b6575060005b5060018060c1575060005b505b56", "srcmap": "0:311:1:-;;;;;;;;;", "srcmap-runtime": "0:311:1:-;;;;;;;;;;;;;;;;;;17:291;;;;;;;;;;;;;;47:4;;61:3;;74;;87;;100;;113;;126:5;;141;;156;;175:1;171;:5;;190:1;186;:5;;206:1;201;:6;;;222:1;217;:6;;;238:1;233;:6;;254:1;249;:6;;;265:4;:13;;;;;273:5;265:13;;288:4;:13;;;;296:5;288:13;;17:291;:::o", "filenames": {"absolute": "/home/monty/tob/tools/slither/tests/ast-parsing/binaryoperation-0.4.0.sol", "used": "/home/monty/tob/tools/slither/tests/ast-parsing/binaryoperation-0.4.0.sol", "short": "tests/ast-parsing/binaryoperation-0.4.0.sol", "relative": "tests/ast-parsing/binaryoperation-0.4.0.sol"}, "libraries": {}, "is_dependency": false, "userdoc": {"methods": {}, "notice": null}, "devdoc": {"methods": {}, "author": null, "details": null, "title": null}}}}, "filenames": [{"absolute": "/home/monty/tob/tools/slither/tests/ast-parsing/binaryoperation-0.4.0.sol", "used": "/home/monty/tob/tools/slither/tests/ast-parsing/binaryoperation-0.4.0.sol", "short": "tests/ast-parsing/binaryoperation-0.4.0.sol", "relative": "tests/ast-parsing/binaryoperation-0.4.0.sol"}]}}, "package": null, "working_dir": "/home/monty/tob/tools/slither", "type": 1, "unit_tests": [], "crytic_version": "0.0.1", "source_content": {"/home/monty/tob/tools/slither/tests/ast-parsing/binaryoperation-0.4.0.sol": "contract C {\n    function f() public {\n        1**2;\n        1*2;\n        1/2;\n        1&2;\n        1+2;\n        1-2;\n        1 & 2;\n        1 ^ 2;\n        1 | 2;\n        1 < 2;\n        1 > 2;\n        1 <= 2;\n        1 >= 2;\n        1 == 2;\n        1 != 2;\n        true && false;\n        true || false;\n    }\n\n}"}}